{
  "title": "Death",
  "pageid": 387836,
  "url": "https://marvelcinematicuniverse.fandom.com/wiki/Death",
  "timestamp": "2026-02-19T22:35:43Z",
  "content": "{{CharHub|Death|Death}}\n{{Character\n|image = Death Infobox.png\n|real name = Death{{Ref|AAA107}}\n|alias = {{Alias\n|codenames = Lady Death<ref>[https://x.com/MarvelStudios/status/1853165252848042273 Marvel Studios on X - November 3, 2024]</ref><br>Green Witch{{Ref|AAA104}}<br>Rio Vidal{{Ref|AAA101}}\n|undercover = Agent Rio Vidal{{ref|AAA101}}}}\n|species = [[Cosmic Entity]]\n|citizenship = \n|DOB = [[Before 20th Century|Dawn of Time]]{{Ref|TAoGotG}}\n|gender = Female\n|title = [[:Category:Green Witches|Green Witch]]<br>{{WPS|Death (tarot card)|Death}}\n|affiliation = \n|movie = {{Infobox List|{{Collapse|''[[The Avengers]]'' <small>(mentioned)</small><br>''[[Guardians of the Galaxy (film)|Guardians of the Galaxy]]'' <small>(art)</small><br>''[[Thor: Love and Thunder]]'' <small>(art)</small>}}}}\n|tv series = ''[[Agatha All Along]]'' <small>(6 episodes)</small>\n|comic = {{Infobox List|{{Collapse|''[[The Avengers (comic)|The Avengers]]'' <small>(mentioned)</small>}}}}\n|actor = [[Aubrey Plaza]]\n|status = Existing}}\n{{Quote|In the end, all roads lead to me.|Death|Death's Hand in Mine}}\n'''Death''' is a [[Cosmic Entities|cosmic entity]], the embodiment of death and decay of all living things. She lived on [[Earth]] as the original [[:Category:Green Witches|Green Witch]] under the name '''Rio Vidal''', and started a relationship with [[Agatha Harkness]]. Nearly [[2026|three centuries later]], Death freed Harkness from a spell she had been placed under by [[Scarlet Witch]] and sent the [[Salem Seven]], a coven with a grudge against Harkness, after her. Later, Vidal was summoned to the [[Witches' Road]] by Harkness and her [[Agatha Harkness' Coven|coven]], who had escaped the Seven when they [[Attack on Agnes O'Connor's House|attacked]], as a replacement green witch. Death came into conflict with Harkness on the Road because she wanted to claim the soul of [[Billy Maximoff]], who had violated the natural order. The tension came to a head in a vicious [[Skirmish at Agnes O'Connor's House|duel]], during which Harkness sacrificed herself to Death to save Maximoff.\n\n==Biography==\n{{MD|Death (Earth-199999)}}\n===Legend===\n{{Quote|Death embodies decay and can possess the soul of a living being. Often taking the form of a woman, Death can manipulate reality, time, and space, and came into existence at the same time as [[Entropy]], [[Eternity]], and [[Infinity]]. Immortals are immune to Death's ability.|Description|The Art of Guardians of the Galaxy}}\nDeath came into existence at the [[Before 20th Century|dawn of time]] along with [[Eternity]], [[Infinity]], and [[Entropy]].{{Ref|TAoGotG}} The walls of the [[Temple Vault]] on [[Morag]] displayed [[Entropy]], [[Infinity]], Death, and [[Eternity]] surrounding the [[Infinity Stones]].{{Ref|GotG}} At the [[Gates of Eternity]], Death has a statue alongside statues of Eternity, the [[Living Tribunal]], [[Watcher]], [[Eon]], the [[One Above All]], and Infinity.{{Ref|TLaT}} Death manifested on Earth as the original Green Witch, going by the name Rio Vidal.{{Ref|AAA108}}\n\n===Relationship with Agatha Harkness===\n====Falling in Love====\n{{Quote|A long time ago, I loved [[Agatha Harkness|someone]].|Rio Vidal|If I Can't Reach You / Let My Song Teach You}}\nDeath, as Vidal, met a witch named [[Agatha Harkness]], who learned about her true identity. The two fell deeply in love, with Harkness being responsible for supplying Vidal with many deaths, much to her delight.{{Ref|AAA109}} \n\n====Hurting Agatha Harkness====\n[[File:Death green cloak.png|{{AltFloat}}|Death gives [[Agatha Harkness]] more time]]\n{{Quote|You do this and I will hate you forever. Please let [[Nicholas Scratch|him]] live. Please, my love! Please! Please! Please!\"<br>\"I can offer only time.|[[Agatha Harkness]] and Death|Maiden Mother Crone}}\nDeath impregnated [[Agatha Harkness]],{{Ref|RioNicky}} and when she went into labor, Death arrived to collect her [[Nicholas Scratch|son]], as he was not supposed to live. Harkness saw Death and told her that she would hate her forever if she took her child away from her. However, despite how much she did not want to do it due to how much it would hurt her love, Death stated that she could only give Harkness more time with her son, before disappearing.{{Ref|AAA109}}\n\n====Taking Nicholas Scratch====\n[[File:Agatha All Along Teaser Trailer (88).png|{{AltFloat}}|Death arrives to collect [[Nicholas Scratch]]]]\n{{Quote|And I had to do something that I did not wanna do, even though it was my job. And it hurt [[Agatha Harkness|them]].|Rio Vidal|If I Can't Reach You / Let My Song Teach You}}\nAfter six years, Death returned for [[Nicholas Scratch]], as his time was up. While he was asleep next to [[Agatha Harkness]], Death appeared once Scratch died, silently signaling him to come with her. Scratch got up, but Death told him to say goodbye to his mother first, so Scratch kissed Harkness' forehead. Death then took Scratch's hand and guided him as they walked away.{{Ref|AAA109}}\n\n====Betrayal Over the Darkhold====\n{{Quote|How long has it been, Agatha? Since you acquired the [[Darkhold]], you hid behind all that dark magic.|Rio Vidal to [[Agatha Harkness]]|Seekest Thou the Road}}\nEventually, [[Agatha Harkness]] found the [[Darkhold]] and became corrupted by the dark magic, which strained her relationship with Death. From then on, the two despised each other, although Death was still in love with Harkness.{{Ref|AAA101}}{{Ref|AAA104}}\n\n===Freeing an Enemy===\n====Agent Vidal====\n[[File:Agent Rio Vidal.png|{{AltFloat}}|Vidal poses as a federal agent]]\n{{Quote|Not a leaf disturbed before Forensics showed up. It's almost like [[Scarlet Witch|she]] just magically appeared.|Rio Vidal to [[Agnes O'Connor]]|Seekest Thou the Road}}\nVidal arrived in [[Westview]] and found [[Agatha Harkness]] under the [[Scarlet Witch]]'s spell as \"Agnes O'Connor.\" O'Connor believed she was a detective for the [[Westview Police Department]]. Therefore, Vidal posed as a federal agent and made her move. She appeared in front of O'Connor, who believed she was working on a murder case. Seeing Vidal, O'Connor got very annoyed. Vidal sat down and O'Connor believed she was there to take her job. Vidal denounced this, saying that O'Connor could take control.\n[[File:Special Agent Rio Vidal.png|{{AltFloat}}|Vidal toys with [[Agnes O'Connor]]]]\nO'Connor then stated that the [[Scarlet Witch|Jane Doe]] was moved across state lines, so that must have been Vidal's play to get the case. Vidal simply asked if that was how she saw herself: as Detective Agnes O'Connor. However, Vidal decided to play along with O'Connor's disillusions, saying they would talk about the case. Vidal pointed out that there were no footprints next to the corpse, meaning she must have \"magically\" appeared. Vidal chose her words carefully to break Harkness' spell. To get further into O'Connor's thoughts, Vidal tried to convince O'Connor she lived in Westview her whole life in an attempt to use reverse psychology. O'Connor then told Vidal to leave.{{Ref|AAA101}}\n\n====Next Move====\n[[File:Agnes and Rio.png|{{AltFloat}}|Vidal tries to gauge [[Agnes O'Connor]]'s spell]]\n{{Quote|Do you remember why you hate me?|Rio Vidal to [[Agnes O'Connor]]|Seekest Thou the Road}}\nVidal later showed up at [[Agnes O'Connor's House]], stating that a female detective cannot have a good career and a good personal life at the same time. She then revealed she brought pizza. As the two started drinking, [[Agnes O'Connor]] said she had a lead in the case, but Vidal said that was not why she came over, but she could continue. O'Connor talked about how they found the body in [[Eastview]]. Vidal then played her next card, saying O'Connor would not go that far out of Westview. O'Connor argued, but Vidal asked where else she had been. This got O'Connor to think.\n[[File:Rio warns Agnes.png|{{AltFloat}}|Vidal tells [[Agnes O'Connor]] to stop]]\nVidal then leaned in and asked O'Connor if she remembered why she hated her. O'Connor realized she did not. Vidal then asked if she hid evidence, which O'Connor also said no to. Vidal simply said she was only lying to herself. Suddenly, O'Connor heard a commotion upstairs and found a [[Teen]] breaking and entering. O'Connor snatched him up. Vidal then watched as O'Connor interrogated the Teen, believing they were at the precinct. Vidal had to tell her to calm down before she left herself.{{Ref|AAA101}}\n\n====[[Liberation of Agatha Harkness]]====\n[[File:Agatha All Along - Detective Rio.jpg|{{AltFloat}}|Vidal reveals [[Scarlet Witch]]'s spell is broken]]\n{{Quote|I am not the only one that wants to see you dead. Wants to see you burn. Or hang or drown.|Rio Vidal to [[Agatha Harkness]]|Seekest Thou the Road}}\nVidal met back up with [[Agnes O'Connor]], who was under the impression she was at the mortuary. Vidal watched as O'Connor started putting the pieces together of what [[Scarlet Witch]] did to her. At this point, Vidal stopped being subtle and started really speaking. She told O'Connor that the witch was gone as well as all of the copies of the [[Darkhold]]. She continued that O'Connor was stuck in a spell and she needed to claw her way out. O'Connor then started to rip away her clothing as she broke away from the spell. She eventually did, returning to Agatha Harkness.\n[[File:Rio Vidal.jpg|{{AltFloat}}|Vidal prepares to fight [[Agatha Harkness]]]]\nWhen Harkness awoke, Vidal slammed through the front door and faced her. She then cast a wind spell before leaping at Harkness with a dagger. Harkness, void of power, blocked the blade. Vidal then talked about their past and Harkness' actions once she got the Darkhold. However, the Darkhold is gone and she was vulnerable. Vidal then pushed the dagger into her throat. However, Harkness was able to break free and the two scuffled.\n[[File:Rio attacks Agatha.png|{{AltFloat}}|Vidal furiously attacking [[Agatha Harkness]]]]\nVidal threw her dagger at Harkness, who blocked it with a baking sheet. They then lunged at the dagger, with Harkness grabbing the blade end. As Vidal pulled it away, the dagger sliced Harkness' hand. Harkness then got the upper hand and started choking Vidal, who said she could not kill her. Harkness said the same for her as it was not allowed. Vidal then headbutted Harkness and used her powers to send her flying into the bureau behind.\n[[File:Rio licks Agatha.png|{{AltFloat}}|Vidal licks and heals [[Agatha Harkness]]' hand]]\nVidal agreed that she could not kill her, but said she could make her wish she were dead. Harkness then told her to stop, begging. Harkness said that Vidal should not kill her in a vulnerable state and instead wait until Harkness had her power back. Vidal agreed, but said she was not the only one who wanted to see her dead, and revealed that [[Salem Seven]] were coming. Before leaving, Vidal licked Harkness' palm, healing her cut.{{Ref|AAA101}}\n\n===[[Walking of the Witches' Road|Walking the Witches' Road]]===\n====Summoned to the Witches' Road====\n[[File:Agatha All Along Trailer (21).png|{{AltFloat}}|Vidal summoned to walk the [[Witches' Road]]]]\n{{Quote|Wow. [[Witches' Road]], huh? Okay.|Rio Vidal|If I Can't Reach You / Let My Song Teach You}}\nVidal was summoned to the [[Witches' Road]] by [[Agatha Harkness]]' [[Agatha Harkness' Coven|coven]] through an incantation, as their previous [[:Category:Green Witches|green witch]] had perished in their [[Potions Witch Trial|first trial]]. Vidal emerged from [[Sharon Davis]]' grave grotesquely contorted, and as she straightened herself out the coven watched in horror.\n[[File:THE Green Witch.png|{{AltFloat}}|Vidal introduces herself to [[Agatha Harkness|Harkness]]' [[Agatha Harkness' Coven|coven]]]]\nVidal greeted the coven, and Harkness asked how she was able to get to the Road, so Vidal joked that she was in the neighborhood. Vidal playfully opened her hand to Harkness, revealing a flower, which enraged Harkness, who crumpled up the flower and tried to attack Vidal, only to be held back by her coven. After Harkness stormed off in frustration, Vidal properly introduced herself to [[Jennifer Kale]], [[Alice Wu-Gulliver]], and [[Lilia Calderu]], clarifying to them that she was \"the\" Green Witch.\n[[File:Do I hate her, or do I want her number?.png|{{AltFloat}}|Vidal listening to the [[Agatha Harkness' Coven|coven]] talk about her]]\nKnowing that they had to walk the Road, Vidal headed off after Harkness and [[Teen]], skipping and whistling as she observed her surroundings. As the coven ventured down the Road, Vidal overheard Kale, Wu-Gulliver, and Calderu talking about her, unsure of whether they were worried or enticed by her. Vidal turned around and playfully scared the three before continuing forwards. The coven arrived at the next trial, which took the form of a [[Witches' Road Recording Studio|house]] that Wu-Gulliver was hesitant to enter, which made Vidal ask if there was a mutiny.{{Ref|AAA104}}\n\n====[[Protection Witch Trial]]====\n[[File:Agatha and Rio.jpeg|{{AltFloat}}|Vidal catching up with [[Agatha Harkness]]]]\n{{Quote|You're too early.\"<br>\"It wasn't up to me. Magick, as it does, took the path of least resistance, ferried the closest, most appropriate candidate down. Or up.|[[Agatha Harkness]] and Rio Vidal|If I Can't Reach You / Let My Song Teach You}}\nVidal followed the [[Agatha Harkness' Coven|coven]] inside the [[Witches' Road Recording Studio]], where their clothes were changed to resemble the [[1970s]]. [[Alice Wu-Gulliver]] told everyone not to touch anything, making Vidal sense there was a larger story behind that. As they checked themselves in the mirror, Vidal playfully asked what came next, so [[Lilia Calderu]] told her a test. The coven members went to look for a clue, leaving Vidal and Harkness. Vidal leaned in close to Harkness, but she sternly rejected her advances and walked off.\n[[File:Rio Smirks.jpg|{{AltFloat}}|Vidal tells [[Agatha Harkness]] her desire to kill]]\nVidal found Harkness by herself and told her that she was growing impatient, wanting to cause some damage, but Harkness said she was too early. Vidal enquired about [[Teen]], but Harkness brushed aside the questioning and asked for a truce between them, reflecting on when they used to be together. Vidal then began talking about killing the other witches, which would give her the bodies that she wanted. However, Vidal realized that Harkness turned the speakers on, letting the coven hear their conversation.\n[[File:Rio Vidal Drumming.jpeg|{{AltFloat}}|Vidal plays the [[Ballad of the Witches' Road]]]]\nThe trial began when Teen put on a record that played a demonic sound, which [[Lilia Calderu]] realized had cursed them all. Vidal was excited by the trial, which confused [[Jennifer Kale]]. When Calderu and Kale fell to the ground in pain, Wu-Gulliver borrowed Vidal's dagger to carve a protection circle around her to save them. After Teen was attacked, Vidal asked Harkness what the plan was, so she figured out that they all needed to play [[Lorna Wu]]'s cover of the [[Ballad of the Witches' Road]], as it was a protection spell against Wu-Gulliver's [[Wu Family Curse|curse]]. The coven performed the song, with Vidal on drums, and they were successful at killing the curse, passing the trial.\n[[File:Agatha and Rio Share a Moment.png|{{AltFloat}}|Vidal has a moment with [[Agatha Harkness]]]]\nThey returned to the [[Witches' Road]], carrying Teen out, as he had been injured. As the witches tended to him, Harkness looked at Vidal and told her not to do anything. Kale was able to heal Teen, and they all rested by a campfire. When Calderu mentioned the misconceptions about witches, Vidal joked about being covered in nipples. Vidal brought up how Harkness was her scar, alluding to when she took [[Nicholas Scratch]], which she did not want to as it hurt Harkness.{{Ref|AAA104}}{{Ref|AAA109}} In private, Vidal and Harkness hugged, but when Harkness tried to kiss Vidal, she stopped it and told her that Teen wasn't her [[Nicholas Scratch|son]].{{Ref|AAA104}}\n\n====[[Ambush on Agatha Harkness' Coven|Escaping the Salem Seven]]====\n[[File:Agatha All Along Teaser Trailer (122).png|{{AltFloat}}|The [[Agatha Harkness' Coven|coven]] escape from the [[Salem Seven]]]]\n{{Quote|When [[Agatha Harkness|Agatha]] [[Trial of Agatha Harkness|murdered]] her [[Salemites|sister witches]], she spared their young children.\"<br>\"Yeah, and then they became a [[Salem Seven|feral, hive-minded coven]] bent on revenge.|[[Lilia Calderu]] and Rio Vidal|Darkest Hour / Wake Thy Power}}\nThe [[Agatha Harkness' Coven|coven]] were awoken by [[Lilia Calderu]], who sensed that the [[Salem Seven]] had followed them on the [[Witches' Road]]. They were soon surrounded, so [[Teen]] suggested they use a hexenbesen to escape, which Vidal was in support of. Vidal and [[Agatha Harkness]] performed the ritual, exchanging brooms with each other, and the coven took to the skies to escape. However, the Road forced them back down, so they headed for the next trial.{{Ref|AAA105}}\n\n====[[Spirit Witch Trial]]====\n[[File:Rio in Agatha's trial.png|{{AltFloat}}|Vidal learns they're in [[Agatha Harkness]]' trial]]\n{{Quote|A minute ago you were ready to slit [[Agatha Harkness|her]] throat.\"<br>\"Yeah, well, her [[Evanora Harkness|mother]] can't have her.|[[Jennifer Kale]] and Rio Vidal|Darkest Hour / Wake Thy Power}}\nThe [[Agatha Harkness' Coven|coven]] entered the [[Witches' Road Cabin]], which Vidal knew was for [[Agatha Harkness]]' trial, seeing the blood moon outside. Figuring out they needed to commune with the dead, [[Teen]] found a {{WPS|Ouija}} board and the trial began.\n[[File:Coven at Sleepover.jpeg|{{AltFloat}}|The [[Agatha Harkness' Coven|coven]] communing with the {{WPS|Ouija}} board]]\nThe coven sat around the board and Harkness led the session. Harkness manipulated the board and pretended to be possessed by the spirit of [[Sharon Davis]], but the coven saw through the act, with Vidal revealing that Harkness was just scared of who from her past might speak to them. They then properly used the board, asking who was with them, and it spelt out \"Death,\" making Vidal laugh. The board then stated that it wanted to punish Harkness, who freaked out and let go of the board. The coven began to discuss how to punish Harkness so they could pass the trial, with Vidal suggesting they slit her throat.\n[[File:Rio talks to Evanora.png|{{AltFloat}}|Vidal refuses to leave [[Agatha Harkness]]]]\nHarkness became possessed and attacked the coven, but she was soon freed. The spirit revealed itself to be Harkness' [[Evanora Harkness|mother]], who scolded the coven for willingly allying with her daughter. She told them that they must complete with [[Witches' Road]] without Harkness. Vidal strongly objected, not wishing to leave Harkness with her mother. When Harkness was possessed again, Vidal witnessed as [[Alice Wu-Gulliver]] freed her, only to be killed as Harkness stole her [[Magic]].{{Ref|AAA105}}\n\n====Taking Alice Wu-Gulliver====\n[[File:Death collects Alice.png|{{AltFloat}}|Death arrives to collect [[Alice Wu-Gulliver]]]]\n{{Quote|That's all the time I get?\"<br>\"If I had a nickel...|[[Alice Wu-Gulliver]] and Death|Follow Me My Friend / To Glory at the End}}\nAs the [[Agatha Harkness' Coven|coven]] returned to the [[Witches' Road]], Death stayed in the [[Witches' Road Cabin|cabin]]. Once [[Alice Wu-Gulliver]] awoke in the afterlife, Death told her it was time to go, revealing that she had died. Wu-Gulliver was disappointed with not having more time, which made Death chuckle, having heard that a lot. Death comforted Wu-Gulliver by telling her that as a Protection Witch, she died protecting [[Agatha Harkness|someone]]. Wu-Gulliver then went with Death.{{Ref|AAA108}}\n\n====Revealing Herself====\n[[File:Lady Death.png|{{AltFloat}}|Vidal is revealed to [[Lilia Calderu]] as Death]]\n{{Quote|Who is that?\"<br>\"Don't you recognize me, Lilia?|[[Lilia Calderu]] and Death|Death's Hand in Mine}}\nVidal later found [[Lilia Calderu]] and [[Jennifer Kale]] underground after being thrown off the [[Witches' Road]]. Calderu asked who Vidal was, so she revealed herself, now in her form as Death, telling her that all roads led to her. Calderu realized Vidal was Death, who revealed herself to Calderu knowing that she would die in the [[Divination Witch Trial|next trial]].{{Ref|AAA107}}\n\n====Making a Deal====\n[[File:Agatha All Along Trailer (40).png|{{AltFloat}}|Death figures out [[Billy Maximoff]]'s identity]]\n{{Quote|[[Wiccan|His]] [[Tommy Maximoff|brother]] isn't out there. Not yet, anyway.\"<br>\"What do you mean?\"<br>\"The son of the [[Scarlet Witch]] stole a [[William Kaplan|second life]]. I can't let him do the same for his twin. I have to take him.|Death and [[Agatha Harkness]]|Follow Me My Friend / To Glory at the End}}\nDeath found [[Agatha Harkness]] on the [[Witches' Road]] and commented on how many members of her [[Agatha Harkness' Coven|coven]] had died, as well as the [[Salem Seven]]. Death admitted that she doubted Harkness on being able to deliver her bodies, suspecting that there would be a twist. Death revealed that she was right about the twist, as Harkness was trying to distract her from [[Billy Maximoff]].\n[[File:Follow Me My Friend To Glory at the End Thumbnail.jpeg|{{AltFloat}}|Death confronts [[Agatha Harkness]]'s actions]]\nDeath told Harkness that Maximoff was an abomination, as his existence disrupted the sacred balance. Death then brought up that she knew how Harkness felt about him, seeing Maximoff like her [[Nicholas Scratch|son]] that she was now walking the Road with. Death stated that no one else had ever received special treatment like Harkness, who only saw what Death did as giving her nothing. Harkness tried to walk away, but Death stopped her, asking why she let people believe the rumors about her trading Scratch for the [[Darkhold]]. Harkness answered Death by saying that it was because the truth was too awful.\n[[File:Death accepts.png|{{AltFloat}}|Death sadly accepts [[Agatha Harkness]]' deal]]\nDeath stated that Maximoff's quest to find his [[Tommy Maximoff|brother]] was a violation. Knowing that Maximoff could bring his brother back to life, Death made it clear that she had to stop him. Harkness told Death to take Maximoff, only to discover that Death required Maximoff to surrender himself to her, as he could just reincarnate if he died again. Harkness decided to deliver Maximoff to Death in exchange for Death leaving her alone forever. Death was heartbroken by this, but ultimately agreed to the deal.{{Ref|AAA108}}\n\n====[[Skirmish at Agnes O'Connor's House]]====\n[[File:Rio Vidal - Death.png|{{AltFloat}}|Death comes to collect [[Agatha Harkness]]]]\n{{Quote|Looks like you two are finally on the same page. So I'll let you decide. One of you stays with me. The other walks free.|Death to [[Agatha Harkness]] and [[Billy Maximoff]]|Follow Me My Friend / To Glory at the End}}\nDeath exited the [[Witches' Road]] and sat on the roof of [[Agatha Harkness]]' [[Agnes O'Connor's House|house]]. When Harkness made it off the Road, Death maniacally cackled as she congratulated her for completing the Road. When Harkness discovered that her powers were still gone, she shouted about wanting her prize, which Death also expressed wanting what was owed to her.\n[[File:Agatha All Along Trailer (73).png|{{AltFloat}}|Death violently attacking [[Agatha Harkness]]]]\nHarkness claimed that she held up her end of the deal, as she got [[Billy Maximoff]] out of the Road, but Death pointed out that he did not surrender himself, therefore she would be taking Harkness instead. Death chose to do so by giving Harkness {{WPS|Lingchi|death by a thousand cuts}}, and she used her powers to break the windows so that shards of glass would cut her skin. Harkness tried to create a protection circle, referring to Death as evil as she did, but Death took offence at this, and destroyed the circle.\n[[File:Agatha All Along Trailer (76).png|{{AltFloat}}|Death prepares to kill [[Agatha Harkness]]]]\nDeath then called Harkness a coward and threw a sink at her, which she dodged. Death angrily asked Harkness why she did not want her before cutting her ankle, causing her to fall. As Death descended to the ground, she restrained Harkness with vines, stopping her from healing herself. Death approached the helpless Harkness, drawing her dagger, preparing to finally kill her. However, she was stopped with the arrival of Wiccan, who knocked Death away and gave Harkness her power back.\n[[File:Fighting Death.jpeg|{{AltFloat}}|Death battles against [[Agatha Harkness]]]]\nGetting back up, Death acknowledged Harkness and Wiccan now working together, leading to her giving them the choice as to which one of them surrenders to her, allowing the other to walk free. However, neither agreed to Death's deal, so she attacked Wiccan, launching him backwards into the greenhouse. As Harkness conjured her [[magic]], Death hurled a blast at her, which Harkness was able to block. The two then proceeded to battle, with Death remarking on how power looked good on Harkness, which she replied that everything looked good on her. Death noted that Harkness seemed like she was having fun, before blasting her, causing her to fall down.\n[[File:Agatha kisses Death.png|{{AltFloat}}|Death kisses [[Agatha Harkness]] to death]]\nWiccan returned and saved Harkness by pushing Death into the house. Death returned to the fight, but Wiccan declared that he would sacrifice himself to her to spare Harkness. Death then witnessed as Harkness complied with Wiccan offering himself up, honoring their original deal. Harkness began to walk away, asking Death to fix her house when she was finished. However, Harkness turned around, approached Death, and began to passionately kiss her, choosing to sacrifice herself by absorbing Death's power.\n[[File:Lady Death (2026).jpeg|{{AltFloat}}|Death tells [[Wiccan]] he is allowed to leave]]\nDeath fully embraced Harkness as they kissed, finally getting to bring her end and have Harkness be hers forever. She then watched as Harkness briefly levitated, only to fall backwards on the ground. Once Harkness died, her body immediately decayed before then blending into the ground, sprouting mushrooms and other plants. Death stood over where her lover's body once was before turning to Wiccan and telling him he was free to leave. With balance achieved, Death then walked away.{{Ref|AAA108}}\n\n==Powers and Abilities==\n===Powers===\n{{Quote|You're calling me 'evil'? I am the natural order of all things, baby.|Death to [[Agatha Harkness]]|Follow Me My Friend / To Glory at the End}}\n*'''Cosmic Entity Physiology''': Death is a [[Cosmic Entities|cosmic entity]] who has existed since the dawn of time, alongside other cosmic beings such as [[Eternity]] and [[Infinity]]. She is the embodiment of death in the universe.\n**'''Superhuman Strength''': Death has been shown to hold a superhuman amount of physical strength, allowing her to throw people of equal height to her with a single hand.\n**'''Superhuman Durability''':  Death is unable to be harmed. Death was able to sustain multiple attacks without any bleeding or injuries.\n**'''Superhuman Agility''': In tandem with her air manipulation, Death can move at incredible speeds and is capable of jumping off of walls.\n**'''Amortality:''' As the embodiment of death, Death itself cannot die, since it is not truly alive. As a cosmological concept, the basic laws of the universe would have to change to erase death.\n**'''Levitation''': Upon being knocked to the ground, Death was able to lift herself back up to her feet without pushing herself up with her hands. She was also able to fly down from Harkness’s roof during their duel.\n**'''Nigh-Omnipotence''': As the embodiment of death, Death has near-unlimited power over her aspect of existence.\n***'''Shapeshifting''': Death can effortlessly change between her true cosmic entity form, and her human form Rio Vidal. She is also capable of unnaturally contorting her body, as shown when she entered the [[Witches' Road]].\n***'''Afterlife Transport''': As the cosmic embodiment of death, she has the duty of guiding souls from the physical plane to the afterlife. She took [[Nicholas Scratch]] to the afterlife upon his death, and she also took [[Alice Wu-Gulliver]] to the afterlife after the latter was killed by Harkness.\n***'''Soul Manipulation''': Death can manipulate souls and can return beings from the dead. However, she rarely performs the latter as it would disturb the natural order she oversees.\n***'''Portal Creation''': Death's dagger can cut through space, creating portals through which she can travel. Death created a portal out of the [[Witches' Road]] by cutting through the fabric of reality with her dagger.\n***'''Telepathy''': Death has the ability to mentally interact with others, Death can read minds, communicate telepathically and experience the memories and thoughts of others. As Rio Vidal, Death was able to enter into [[Agatha Harkness]] and interact with the [[Scarlet Witch]]'s [[Westview Anomaly|spell]]. After her duel with Harkness, Death telepathically told [[Billy Maximoff]] he could go.\n***'''Telekinesis''': Death has the ability to move, levitate, and otherwise manipulate objects using her mind. Death was able to shatter windows and telekinetically throw a sink at [[Agatha Harkness]] during their [[Skirmish at Agnes O'Connor's House|duel]]. She was also able to launch Maximoff into a greenhouse.\n***'''Power Absorption Immunity''': Death, as a cosmic entity and the embodiment of mortality, possesses powers that are inherently unabsorbable. Any attempt to absorb them results in the instant death of the individual, as these powers are inseparable from Death's essence.\n***'''Healing''': At the end of her [[Attack on Agatha Harkness|fight]] with [[Agatha Harkness]], Death licked the witch's hand where it had been cut, healing the wound.\n***'''[[Magic]]''': As a [[Cosmic Entities|cosmic entity]], Death wields immense magical power, drawing from the mystical forces of the universe to achieve extraordinary feats.\n****'''[[Magic#Witchcraft|Witchcraft]]''': Death could perform a specific type of magic exclusive to witches known as witchcraft, allowing her to cast spells in the form of hand gestures or incantations.\n*****'''Magical Energy Manipulation''': Death can manifest and control raw magical energy from her body, which appears as green light.\n******'''Energy Projection''': Death was able to blast Harkness with magical green energy during their duel at the latter's [[Agnes O'Connor's House|house]].\n*****'''Spell Casting''': Death has the power to cause change to her surroundings by reciting incantations. She performed a ritual to create a broomstick, giving it the ability to fly.\n*****'''[[Magic#Earth Magic|Earth Magic]]''': Death, as the original Green Witch, was the first user of Earth Magic.\n******'''Elemental Manipulation''': Death can command the elements of earth, air, fire, and water.\n*******'''Air Manipulation''': Death can manipulate the currents of air around her and concentrate them into a focused blast. She was able to create powerful blasts of wind in her fight with Agatha to blow down her door and push her across the room.\n*******'''Fire Manipulation''': Death can create, shape and manipulate the element of fire. When taking [[Nicholas Scratch]]'s soul to the afterlife, Death lit a torch with green fire so that she would be visible to him.\n******'''Plant Manipulation''': Death can create vines to attack and trap her enemies, as she did to Agatha Harkness in their final battle.\n******'''Weather Manipulation''': Death can create and control powerful storms, with the storm clouds tinted green.\n******'''Death Inducement''': Death can instantly kill any living being through varying means. Death was able to instantly kill [[Agatha Harkness]] just by kissing her.\n******'''Decomposition Manipulation''': Death can accelerate the decomposition of organic matter, as she did with the body of Agatha Harkness.\n\n===Abilities===\n*'''Master Sorceress''': Death is a powerful witch, and she sports an arsenal of spells and magical abilities. In her vulnerable state, [[Agatha Harkness]] showed fear of Death, implying that Death may be just as skilled in the art of witchcraft as Harkness.\n*'''Master Combatant''': Death is a warrior witch, making her a formidable fighter. She was able to jump from walls in her [[Attack on Agatha Harkness|fight]] with Harkness  and almost killed her in the process with her dagger.\n*'''Expert Tactician''': During the last few days of Harkness’ [[Westview Anomaly|mental entrapment]], Death was able to seamlessly weave her way into her former lover's mind, taking on the role of her fantasy rival and pulling at the right strings in tandem with [[Billy Maximoff]]’s spell in order to help Harkness [[Liberation of Agatha Harkness|break free]].\n*'''Marksman''': Death can effectively and accurately throw projectiles at her targets. She very nearly hit Harkness with her dagger, but Harkness dodged it in the nick of time.\n*'''Bilingualism''': Death is fluent in English and Latin; she uses the latter of the two to cast spells.\n\n==Equipment==\n*'''Green Witch Dagger''': Death is armed with a small curved bladed dagger which she frequently uses throughout her combat under the guise of Rio Vidal.\n\n==Relationships==\n{{Col-begin}}{{Col-2}}\n===Family===\n*[[Eternity]] - Brother\n*[[Infinity]] - Sister\n*[[Entropy]] - Nephew\n*[[Eon]] - Nephew\n*[[Nicholas Scratch]] † - Son{{Ref|RioNicky}}\n\n===Allies===\n*[[Agatha Harkness' Coven]]\n**[[Lilia Calderu]] †\n**[[Jennifer Kale]]\n**[[Alice Wu-Gulliver]] †\n{{Col-2}}\n\n===Enemies===\n*[[Agatha Harkness]] † - Former Lover, Attempted Killer and Victim\n*[[Wiccan|Billy Maximoff/Wiccan]] - Former Ally and Attempted Victim\n*[[Wu Family Curse]] †\n*[[Salem Seven]] †\n**[[Vertigo]] †\n**[[Coyote]] †\n**[[Crow]] †\n**[[Fox (Salem Seven)|Fox]] †\n**[[Owl]] †\n**[[Rat]] †\n*[[Evanora Harkness]] †\n{{Col-end}}\n\n==Appearances==\n{| class=\"mw-collapsible mw-collapsed wikitable\" width=\"100%\"\n! Appearances for Death\n|-\n|\n{{Scroll box|content=\nIn chronological order:\n*{{Appearance|AAA109}} <small>(flashbacks)</small>\n*{{Appearance|TA}} <small>(mentioned)</small>\n**{{Appearance|TAC2}} <small>(mentioned)</small>\n*{{Appearance|GotG}} <small>(art)</small>\n*{{Appearance|TLaT}} <small>(statue)</small>\n*{{Appearance|AAA101}}\n*{{Appearance|AAA102}} <small>(mentioned)</small>\n*{{Appearance|AAA104}}\n**{{Appearance|AAA107}} <small>(concurrent events)</small>\n*{{Appearance|AAA105}}\n**{{Appearance|AAA107}} <small>(concurrent events)</small>\n*{{Appearance|AAA107}}\n*{{Appearance|AAA108}}\n*{{Appearance|AAA109}} <small>(mentioned)</small>}}\n|}\n\n==Trivia==\n*In the comics, Death is the personification of mortality with powers over death and the afterlife. Death appears in many forms, but most often a woman or a skeleton. [[Thanos]] is in \"love\" with Death, and during ''{{WPS|The Infinity Gauntlet}}'' storyline, he [[Snap|killed half of the universe]] to win her affection despite Death's disinterest in him. Also, Death has shown to actively have a romantic interest for [[Deadpool]], which caused Thanos to put a curse on him so that Deadpool cannot die.\n*Rio Vidal roughly translates to \"river of life.\"\n\n==Behind the Scenes==\n*Death was initially meant to feature as Thanos' motivation for the [[Snap]] in the [[Marvel Cinematic Universe]]. In addition to being mentioned in ''[[The Avengers]]'', [[Josh Brolin]] revealed following the release of ''[[Guardians of the Galaxy (film)|Guardians of the Galaxy]]'' that Thanos' relationship with Death would be explored and that she would be portrayed as a woman in the MCU. In the interview, Brolin stated ''\"His relationship with Death, who is actually the woman, I love that. You can take ''{{WPS|Sin City: A Dame to Kill For|Sin City}}'' and pump it full of steroids, and then you have Thanos. I like that he's motivated by that — not just motivated by destruction or death or this or that. He's motivated by a very identifiable, human trait.\"''<ref>[http://screenrant.com/thanos-josh-brolin-death-avengers/ Josh Brolin Talks Future Thanos Appearances and ‘Death’ Relationship]</ref>\n**However, Death ended up being removed by [[Joe Russo|Joe]] and [[Anthony Russo]], directors of ''[[Avengers: Infinity War]]'', with Joe Russo explaining that they felt the time needed to introduce the character would be better spent focusing on just Thanos and the film's already large cast, stating \"''It's our responsibility to carry forward the story as it's been set out. You're spending two-and-a-half hours with this many characters, so then adding in some character that the audience has no relationship to, having to explain the backstory of that character, making you care about that character, making Thanos care about that character, making that character interesting to the other characters.''\"<ref>[https://www.businessinsider.com/avengers-infinity-war-changes-why-thanos-wants-infinity-stones-2018-4 'Avengers: Infinity War' changes up the bizarre reason Thanos wants the Infinity stones in the comics — here's why]</ref>\n**[[Joss Whedon]] has stated that when he featured Thanos at the end of ''The Avengers'', he didn't know what to do with him and \"''kind of hung [Thanos] out to dry'',\" adding that \"''I love Thanos. I love his apocalyptic vision, his love affair with Death. I love his power. But, I don't really understand it'',\" confirming that his tease was ambiguous when it was made and that the Death storyline was \"''not a concept that will necessarily translate''\". Despite ''Avengers: Infinity War'' ultimately diverting from Thanos' set-up in ''The Avengers'', Whedon enjoyed the new approach the Russo Brothers took as they gave Thanos \"''an actual perspective and [making] him feel righteous to himself''\".<ref>[https://www.ign.com/articles/2018/07/21/joss-whedon-pleased-with-how-avengers-infinity-war-diverted-from-his-thanos-setup-comic-con-2018 JOSS WHEDON PLEASED WITH HOW AVENGERS: INFINITY WAR DIVERTED FROM HIS THANOS SETUP - COMIC-CON 2018]</ref>\n**Commenting on Death's inclusion in ''[[Agatha All Along]]'' and whether or not she is connected to Thanos in any way, [[Jac Schaeffer]] stated: \"''Thanos is not in my show, so I can't speak to any Thanos connections. Thanos stans out there, I have no answers for you.''\"<ref>[https://www.inverse.com/entertainment/jac-schaeffer-teases-more-death-no-thanos-in-agatha-all-alongs-finale Agatha All Along Showrunner Shuts Down A Huge Thanos Theory]</ref>\n*[[Aubrey Plaza]]'s role as Rio Vidal in ''[[Agatha All Along]]'' overlapped with her role of Wow Platinum in ''{{WPS|Megalopolis (film)|Megalopolis}}'' during the show's last two weeks of filming. However, as both projects were shot in the same lot, Plaza was able to do both without many difficulties: \"''I would literally go from one to the other and would put my Wow wig on and my Wow costume on. And then the next day, I would go to the ''Agatha'' set and I’d be dressed as a warrior witch with a dagger and stuff. At one point, when I was dressed in the [[Marvel Comics|Marvel]] character, I snuck onto the ''Megalopolis'' set and I started harassing [[Giancarlo Esposito]] and {{WPS|Adam Driver|Adam}} and everyone. It was absolutely insane behavior''\".<ref name=\"Conflicts\">[https://deadline.com/2024/05/aubrey-plaza-interview-megalopolis-francis-ford-coppola-1235904319/ Cannes Cover Story: Aubrey Plaza Says Francis Coppola “Doesn’t Need My Defense”, Reveals The “Collaboration And Experimentation” Of ‘Megalopolis’]</ref>\n*The dynamic between Death and [[Lilia Calderu]] was developed organically on set by actors [[Aubrey Plaza]] and [[Patti LuPone]].{{Ref|TMoAAA}}\n*[[Hive]], a powerful [[Inhuman]] whom [[Hydra]] revered, was referred to as \"Death\" due to its fearsome nature and reputation.\n*[[Sarah Irwin]] and [[Stephanie Baur]] were stunt doubles for [[Aubrey Plaza]] in the role of Death.\n\n==External Links==\n*{{Marvel}}\n*{{WP|Death (Marvel Comics)|Death}}\n\n==References==\n{{Gallery|Death/Gallery}}\n{{Wq}}\n{{Reflist}}\n\n[[es:Muerte]]\n[[fr:Mort]]\n[[pl:Śmierć]]\n[[pt-br:Morte]]\n[[ru:Смерть]]\n\n[[Category:Characters]]\n[[Category:Agatha All Along Characters]]\n[[Category:Cosmic Entities]]\n[[Category:Females]]\n[[Category:Black Hair]]\n[[Category:Brown Eyes]]\n[[Category:Witches]]\n[[Category:Green Witches]]\n[[Category:High Body Count]]\n[[Category:LGBTQIA+ Characters]]",
  "infobox": {
    "image": "Death Infobox.png",
    "real name": "Death{{Ref|AAA107",
    "alias": "{{Alias",
    "codenames": "Lady Death<ref>[https://x.com/MarvelStudios/status/1853165252848042273 Marvel Studios on X - November 3, 2024]</ref><br>Green Witch{{Ref|AAA104}}<br>Rio Vidal{{Ref|AAA101",
    "undercover": "Agent Rio Vidal{{ref|AAA101",
    "species": "[[Cosmic Entity]]",
    "citizenship": "",
    "DOB": "[[Before 20th Century|Dawn of Time]]{{Ref|TAoGotG",
    "gender": "Female",
    "title": "[[:Category:Green Witches|Green Witch]]<br>{{WPS|Death (tarot card)|Death",
    "affiliation": "",
    "movie": "{{Infobox List|{{Collapse|''[[The Avengers]]'' <small>(mentioned)</small><br>''[[Guardians of the Galaxy (film)|Guardians of the Galaxy]]'' <small>(art)</small><br>''[[Thor: Love and Thunder]]'' <small>(art)</small>",
    "tv series": "''[[Agatha All Along]]'' <small>(6 episodes)</small>",
    "comic": "{{Infobox List|{{Collapse|''[[The Avengers (comic)|The Avengers]]'' <small>(mentioned)</small>",
    "actor": "[[Aubrey Plaza]]",
    "status": "Existing"
  },
  "cineverse_id": "rio-vidal",
  "cineverse_name": "Rio Vidal"
}